[
    {
        "platform": "trendyol",
        "external_id": "917839766",
        "title": "Samsung Galaxy A26 5G 256 GB Akıllı Telefon Beyaz (Samsung Türkiye Garantili) Galaxy A26 5G 256 GB Akıllı Telefon Beyaz (Samsung Türkiye Garantili)",
        "price": 111579917769.93,
        "currency": "TRY",
        "image_url": "https://cdn.dsmcdn.com/mnresize/400/-/ty1811/prod/QC_PREP/20260108/15/51e096e3-ef88-34ed-a6a2-26b2e38b82a9/1_org_zoom.jpg",
        "image_urls": [
            "https://cdn.dsmcdn.com/mnresize/620/920/ty1811/prod/QC_PREP/20260108/15/51e096e3-ef88-34ed-a6a2-26b2e38b82a9/1_org_zoom.jpg",
            "https://cdn.dsmcdn.com/mnresize/620/920/ty1809/prod/QC_PREP/20260108/15/b7594a0b-ea8d-3d46-9e42-d218316691ce/1_org_zoom.jpg",
            "https://cdn.dsmcdn.com/mnresize/128/-/indexing-sticker-stamp/mars/81901534-f3f6-4495-8d32-d2bcc648ec11.png",
            "https://cdn.dsmcdn.com/mnresize/128/-/indexing-sticker-stamp/mars/bc279028-2fde-461a-80ba-df1c7e816910.png",
            "https://cdn.dsmcdn.com/mnresize/620/920/ty1809/prod/QC_PREP/20260108/15/d5adadcb-7f62-397b-a07d-05a5c4825590/1_org_zoom.jpg",
            "https://cdn.dsmcdn.com/mnresize/-/49/ty925/product/inventory/vas/seller-logo-463180-trendyol-sigorta-1002.jpg",
            "https://cdn.dsmcdn.com/mnresize/-/49/ty924/product/inventory/vas/seller-logo-463180-trendyol-sigorta-1001.jpg",
            "https://cdn.dsmcdn.com/mnresize/-/49/ty925/product/inventory/vas/seller-logo-463180-trendyol-sigorta-1008.jpg",
            "https://cdn.dsmcdn.com/web/prod/fp/ai1_1744811068004.svg",
            "https://cdn.dsmcdn.com/web/prod/fp/info_1744805921885.svg",
            "https://cdn.dsmcdn.com/web/production/placeholder-card.svg"
        ],
        "product_url": "https://www.trendyol.com/samsung/galaxy-a26-5g-256-gb-akilli-telefon-beyaz-samsung-turkiye-garantili-p-917839766?boutiqueId=689770&merchantId=968",
        "description": "Bu ürün \nTrendyol\n tarafından gönderilecektir.\nKampanya fiyatından satılmak üzere 100 adetten fazla stok sunulmuştur.\nİncelemiş olduğunuz ürünün satış fiyatını satıcı belirlemektedir.\nÜrüne ait garanti belgesi ile tanıtma ve kullanım kılavuzları; kağıt ortamında paylaşılabileceği gibi elektronik ortamda erişim sağlayabileceğiniz, link ve karekod biçiminde de sunulabilecektir. Ürün teslimi sonrası ambalajın, paketin, kutunun dikkatle açılması tavsiye edilir.\n\nÜrün Özellikleri:\n- Dahili Hafıza: 256 GB\n- Ekran Boyutu: 6,7 inç\n- Garanti Tipi: Resmi Distribütör Garantili\n- Kamera Çözünürlüğü: 20 MP ve üstü\n- RAM Kapasitesi: 6 GB\n- Pil Gücü (mAh): 5000 ve üstü\n- Mobil Bağlantı Hızı: 4.5G\n- Yüz Tanıma: Var\n- Kulaklık Girişi: 3.5 mm\n- Ana Kamera Flaş: Var\n- Batarya Kapasitesi Aralığı: 5000-6000 mAh\n- Ekran Teknolojisi: Dinamik AMOLED\n- Suya/Toza Dayanıklılık: Var\n- Ön Kamera Çözünürlüğü: 8 MP ve üstü\n- Dokunmatik Ekran: Var\n- Ön Kamera Flaş: Var\n- Şarj Hızı: 20-40 W\n- Şarj Girişi: USB Type-C\n- Ekran Çözünürlüğü: FHD+\n- Ekran Cinsi: Super AMOLED\n- Ekran Boyut Aralığı: 6.5'' - 7''\n- Ekran Yenileme Hızı: 120 Hz\n- Cep Telefonu Modeli: Samsung Galaxy A26\n- Ön Kamera Sayısı: 1\n- Ön Kamera Çözünürlük Aralığı: 15 - 20 MP\n- Görüntü Teknolojisi: AMOLED\n- Arka Kamera Sayısı: 1\n- İşletim Sistemi: Android\n- Çift Hat: Var\n- Kablosuz Şarj: Yok\n- Garanti Süresi: 2 Yıl\n- Ana Kamera Çözünürlük Aralığı: 40 - 60 MP\n- Renk: Beyaz\n- NFC: Var\n- Video Kayıt Çözünürlüğü: 2160p (Ultra HD) 4K\n- Arttırılabilir Hafıza (Hafıza Kartı Desteği): Var\n- Parmak İzi Okuyucu: Var\n- Yapay Zeka: Var\n- Özellik: Kablosuz\n\nEk Bilgiler:\n- Kargo: kargonun bedava\n- İade Koşulu: 15 gün içinde ücretsiz iade\n- Barkod No: 8806097100645",
        "rating": 4.532738095238095,
        "reviews_count": 673,
        "stock": 10,
        "brand": "Samsung Galaxy A26 5G 256 GB Akıllı Telefon Beyaz (Samsung Türkiye Garantili)",
        "category": "Trendyol",
        "subcategory": "Samsung > Elektronik > Telefon > Cep Telefonu > Android Cep Telefonu > Samsung Android Cep Telefonu > Elektronik > Telefon > Cep Telefonu > Android Cep Telefonu > Samsung Android Cep Telefonu > Samsung Galaxy A26 5G 256 GB Akıllı Telefon Beyaz (Samsung Türkiye Garantili)",
        "attributes": {
            "Dahili Hafıza": "256 GB",
            "Ekran Boyutu": "6,7 inç",
            "Garanti Tipi": "Resmi Distribütör Garantili",
            "Kamera Çözünürlüğü": "20 MP ve üstü",
            "RAM Kapasitesi": "6 GB",
            "Pil Gücü (mAh)": "5000 ve üstü",
            "Mobil Bağlantı Hızı": "4.5G",
            "Yüz Tanıma": "Var",
            "Kulaklık Girişi": "3.5 mm",
            "Ana Kamera Flaş": "Var",
            "Batarya Kapasitesi Aralığı": "5000-6000 mAh",
            "Ekran Teknolojisi": "Dinamik AMOLED",
            "Suya/Toza Dayanıklılık": "Var",
            "Ön Kamera Çözünürlüğü": "8 MP ve üstü",
            "Dokunmatik Ekran": "Var",
            "Ön Kamera Flaş": "Var",
            "Şarj Hızı": "20-40 W",
            "Şarj Girişi": "USB Type-C",
            "Ekran Çözünürlüğü": "FHD+",
            "Ekran Cinsi": "Super AMOLED",
            "Ekran Boyut Aralığı": "6.5'' - 7''",
            "Ekran Yenileme Hızı": "120 Hz",
            "Cep Telefonu Modeli": "Samsung Galaxy A26",
            "Ön Kamera Sayısı": "1",
            "Ön Kamera Çözünürlük Aralığı": "15 - 20 MP",
            "Görüntü Teknolojisi": "AMOLED",
            "Arka Kamera Sayısı": "1",
            "İşletim Sistemi": "Android",
            "Çift Hat": "Var",
            "Kablosuz Şarj": "Yok",
            "Garanti Süresi": "2 Yıl",
            "Ana Kamera Çözünürlük Aralığı": "40 - 60 MP",
            "Renk": "Beyaz",
            "NFC": "Var",
            "Video Kayıt Çözünürlüğü": "2160p (Ultra HD) 4K",
            "Arttırılabilir Hafıza (Hafıza Kartı Desteği)": "Var",
            "Parmak İzi Okuyucu": "Var",
            "Yapay Zeka": "Var",
            "Özellik": "Kablosuz"
        },
        "additional_info": {
            "Kargo": "kargonun bedava",
            "İade Koşulu": "15 gün içinde ücretsiz iade",
            "Barkod No": "8806097100645"
        }
    },
    {
        "platform": "trendyol",
        "external_id": "917839767",
        "title": "Samsung Galaxy A26 5G 256 GB Akıllı Telefon Pembe (Samsung Türkiye Garantili) Galaxy A26 5G 256 GB Akıllı Telefon Pembe (Samsung Türkiye Garantili)",
        "price": 91579917391.36,
        "currency": "TRY",
        "image_url": "https://cdn.dsmcdn.com/mnresize/400/-/ty1811/prod/QC_PREP/20260108/15/f34e24e1-4173-34e6-a4dc-1e50ba5ae97f/1_org_zoom.jpg",
        "image_urls": [
            "https://cdn.dsmcdn.com/mnresize/620/920/ty1811/prod/QC_PREP/20260108/15/f34e24e1-4173-34e6-a4dc-1e50ba5ae97f/1_org_zoom.jpg",
            "https://cdn.dsmcdn.com/mnresize/620/920/ty1810/prod/QC_PREP/20260108/15/de929043-060d-3756-b519-b0c891db3d5f/1_org_zoom.jpg",
            "https://cdn.dsmcdn.com/mnresize/128/-/indexing-sticker-stamp/mars/81901534-f3f6-4495-8d32-d2bcc648ec11.png",
            "https://cdn.dsmcdn.com/mnresize/106/-/indexing-sticker-stamp/moon/75439ab0-63fd-470d-8c1a-8d2fb65a3a35.png",
            "https://cdn.dsmcdn.com/mnresize/620/920/ty1809/prod/QC_PREP/20260108/15/bf04732b-aff8-3d84-bf3a-2d977157b533/1_org_zoom.jpg",
            "https://cdn.dsmcdn.com/mnresize/-/49/ty925/product/inventory/vas/seller-logo-463180-trendyol-sigorta-1002.jpg",
            "https://cdn.dsmcdn.com/mnresize/-/49/ty924/product/inventory/vas/seller-logo-463180-trendyol-sigorta-1001.jpg",
            "https://cdn.dsmcdn.com/mnresize/-/49/ty925/product/inventory/vas/seller-logo-463180-trendyol-sigorta-1008.jpg",
            "https://cdn.dsmcdn.com/web/prod/fp/ai1_1744811068004.svg",
            "https://cdn.dsmcdn.com/web/prod/fp/info_1744805921885.svg",
            "https://cdn.dsmcdn.com/web/production/placeholder-card.svg"
        ],
        "product_url": "https://www.trendyol.com/samsung/galaxy-a26-5g-256-gb-akilli-telefon-pembe-samsung-turkiye-garantili-p-917839767?boutiqueId=689770&merchantId=968",
        "description": "Bu ürün \nTrendyol\n tarafından gönderilecektir.\nKampanya fiyatından satılmak üzere 5 adetten az stok bulunmaktadır.\nÜrüne ait garanti belgesi ile tanıtma ve kullanım kılavuzları; kağıt ortamında paylaşılabileceği gibi elektronik ortamda erişim sağlayabileceğiniz, link ve karekod biçiminde de sunulabilecektir. Ürün teslimi sonrası ambalajın, paketin, kutunun dikkatle açılması tavsiye edilir.\nBir ürün, birden fazla satıcı tarafından satılabilir. Birden fazla satıcı tarafından satışa sunulan ürünlerin satıcıları ürün için belirledikleri fiyata, satıcı puanlarına, teslimat statülerine, ürünlerdeki promosyonlara, kargonun bedava olup olmamasına ve ürünlerin hızlı teslimat ile teslim edilip edilememesine, ürünlerin stok ve kategorileri bilgilerine göre sıralanmaktadır.\n\nÜrün Özellikleri:\n- Dahili Hafıza: 256 GB\n- Ekran Boyutu: 6,7 inç\n- Garanti Tipi: Resmi Distribütör Garantili\n- Kamera Çözünürlüğü: 20 MP ve üstü\n- RAM Kapasitesi: 6 GB\n- Pil Gücü (mAh): 5000 ve üstü\n- Mobil Bağlantı Hızı: 4.5G\n- Ana Kamera Flaş: Var\n- Kulaklık Girişi: 3.5 mm\n- Suya/Toza Dayanıklılık: Var\n- Batarya Kapasitesi Aralığı: 5000-6000 mAh\n- Ekran Teknolojisi: Dinamik AMOLED\n- Yüz Tanıma: Var\n- Ön Kamera Çözünürlüğü: 8 MP ve üstü\n- Dokunmatik Ekran: Var\n- Ön Kamera Flaş: Var\n- Şarj Hızı: 20-40 W\n- Şarj Girişi: USB Type-C\n- Ekran Çözünürlüğü: FHD+\n- Ekran Cinsi: Super AMOLED\n- Ekran Boyut Aralığı: 6.5'' - 7''\n- Ekran Yenileme Hızı: 120 Hz\n- Cep Telefonu Modeli: Samsung Galaxy A26\n- Ön Kamera Sayısı: 1\n- Ön Kamera Çözünürlük Aralığı: 15 - 20 MP\n- Görüntü Teknolojisi: AMOLED\n- Arka Kamera Sayısı: 1\n- İşletim Sistemi: Android\n- Çift Hat: Var\n- Kablosuz Şarj: Yok\n- Garanti Süresi: 2 Yıl\n- Renk: Pembe\n- Ana Kamera Çözünürlük Aralığı: 40 - 60 MP\n- NFC: Var\n- Video Kayıt Çözünürlüğü: 2160p (Ultra HD) 4K\n- Arttırılabilir Hafıza (Hafıza Kartı Desteği): Var\n- Parmak İzi Okuyucu: Var\n- Yapay Zeka: Var\n- Özellik: Kablosuz\n\nEk Bilgiler:\n- Kargo: kargonun bedava\n- İade Koşulu: 15 gün içinde ücretsiz iade\n- Barkod No: 8806097100652",
        "rating": 4.776859504132231,
        "reviews_count": 121,
        "stock": 10,
        "brand": "Samsung Galaxy A26 5G 256 GB Akıllı Telefon Pembe (Samsung Türkiye Garantili)",
        "category": "Trendyol",
        "subcategory": "Samsung > Elektronik > Telefon > Cep Telefonu > Android Cep Telefonu > Samsung Android Cep Telefonu > Elektronik > Telefon > Cep Telefonu > Android Cep Telefonu > Samsung Android Cep Telefonu > Samsung Galaxy A26 5G 256 GB Akıllı Telefon Pembe (Samsung Türkiye Garantili)",
        "attributes": {
            "Dahili Hafıza": "256 GB",
            "Ekran Boyutu": "6,7 inç",
            "Garanti Tipi": "Resmi Distribütör Garantili",
            "Kamera Çözünürlüğü": "20 MP ve üstü",
            "RAM Kapasitesi": "6 GB",
            "Pil Gücü (mAh)": "5000 ve üstü",
            "Mobil Bağlantı Hızı": "4.5G",
            "Ana Kamera Flaş": "Var",
            "Kulaklık Girişi": "3.5 mm",
            "Suya/Toza Dayanıklılık": "Var",
            "Batarya Kapasitesi Aralığı": "5000-6000 mAh",
            "Ekran Teknolojisi": "Dinamik AMOLED",
            "Yüz Tanıma": "Var",
            "Ön Kamera Çözünürlüğü": "8 MP ve üstü",
            "Dokunmatik Ekran": "Var",
            "Ön Kamera Flaş": "Var",
            "Şarj Hızı": "20-40 W",
            "Şarj Girişi": "USB Type-C",
            "Ekran Çözünürlüğü": "FHD+",
            "Ekran Cinsi": "Super AMOLED",
            "Ekran Boyut Aralığı": "6.5'' - 7''",
            "Ekran Yenileme Hızı": "120 Hz",
            "Cep Telefonu Modeli": "Samsung Galaxy A26",
            "Ön Kamera Sayısı": "1",
            "Ön Kamera Çözünürlük Aralığı": "15 - 20 MP",
            "Görüntü Teknolojisi": "AMOLED",
            "Arka Kamera Sayısı": "1",
            "İşletim Sistemi": "Android",
            "Çift Hat": "Var",
            "Kablosuz Şarj": "Yok",
            "Garanti Süresi": "2 Yıl",
            "Renk": "Pembe",
            "Ana Kamera Çözünürlük Aralığı": "40 - 60 MP",
            "NFC": "Var",
            "Video Kayıt Çözünürlüğü": "2160p (Ultra HD) 4K",
            "Arttırılabilir Hafıza (Hafıza Kartı Desteği)": "Var",
            "Parmak İzi Okuyucu": "Var",
            "Yapay Zeka": "Var",
            "Özellik": "Kablosuz"
        },
        "additional_info": {
            "Kargo": "kargonun bedava",
            "İade Koşulu": "15 gün içinde ücretsiz iade",
            "Barkod No": "8806097100652"
        }
    },
    {
        "platform": "trendyol",
        "external_id": "917839671",
        "title": "Samsung Galaxy A26 5G 256 GB Akıllı Telefon Siyah (Samsung Türkiye Garantili) Galaxy A26 5G 256 GB Akıllı Telefon Siyah (Samsung Türkiye Garantili)",
        "price": 1579916627.82,
        "currency": "TRY",
        "image_url": "https://cdn.dsmcdn.com/mnresize/400/-/ty1810/prod/QC_PREP/20260108/15/89cd8bbe-2c8b-301e-a421-9a8f7a5f5e0e/1_org_zoom.jpg",
        "image_urls": [
            "https://cdn.dsmcdn.com/mnresize/620/920/ty1810/prod/QC_PREP/20260108/15/89cd8bbe-2c8b-301e-a421-9a8f7a5f5e0e/1_org_zoom.jpg",
            "https://cdn.dsmcdn.com/mnresize/620/920/ty1811/prod/QC_PREP/20260108/15/e1751d3d-6a1b-367c-b5f5-c96dc90567db/1_org_zoom.jpg",
            "https://cdn.dsmcdn.com/mnresize/128/-/indexing-sticker-stamp/mars/81901534-f3f6-4495-8d32-d2bcc648ec11.png",
            "https://cdn.dsmcdn.com/mnresize/128/-/indexing-sticker-stamp/mars/bc279028-2fde-461a-80ba-df1c7e816910.png",
            "https://cdn.dsmcdn.com/mnresize/620/920/ty1811/prod/QC_PREP/20260108/15/4df33ec7-126b-3091-a32a-cc54bfe9ba93/1_org_zoom.jpg",
            "https://cdn.dsmcdn.com/mnresize/620/920/ty1810/prod/QC_PREP/20260108/15/baa97c8d-774e-33f0-acc2-3431148ca15d/1_org_zoom.jpg",
            "https://cdn.dsmcdn.com/mnresize/-/49/ty925/product/inventory/vas/seller-logo-463180-trendyol-sigorta-1002.jpg",
            "https://cdn.dsmcdn.com/mnresize/-/49/ty924/product/inventory/vas/seller-logo-463180-trendyol-sigorta-1001.jpg",
            "https://cdn.dsmcdn.com/mnresize/-/49/ty925/product/inventory/vas/seller-logo-463180-trendyol-sigorta-1008.jpg",
            "https://cdn.dsmcdn.com/web/prod/fp/ai1_1744811068004.svg",
            "https://cdn.dsmcdn.com/web/prod/fp/info_1744805921885.svg",
            "https://cdn.dsmcdn.com/web/production/placeholder-card.svg"
        ],
        "product_url": "https://www.trendyol.com/samsung/galaxy-a26-5g-256-gb-akilli-telefon-siyah-samsung-turkiye-garantili-p-917839671?boutiqueId=689770&merchantId=968",
        "description": "Bu ürün \nTrendyol\n tarafından gönderilecektir.\nKampanya fiyatından satılmak üzere 100 adetten fazla stok sunulmuştur.\nİncelemiş olduğunuz ürünün satış fiyatını satıcı belirlemektedir.\nÜrüne ait garanti belgesi ile tanıtma ve kullanım kılavuzları; kağıt ortamında paylaşılabileceği gibi elektronik ortamda erişim sağlayabileceğiniz, link ve karekod biçiminde de sunulabilecektir. Ürün teslimi sonrası ambalajın, paketin, kutunun dikkatle açılması tavsiye edilir.\n\nÜrün Özellikleri:\n- Ekran Boyutu: 6,7 inç\n- Dahili Hafıza: 256 GB\n- Garanti Tipi: Resmi Distribütör Garantili\n- Kamera Çözünürlüğü: 20 MP ve üstü\n- RAM Kapasitesi: 6 GB\n- Pil Gücü (mAh): 5000 ve üstü\n- Mobil Bağlantı Hızı: 4.5G\n- Ekran Teknolojisi: Dinamik AMOLED\n- Kulaklık Girişi: 3.5 mm\n- Ana Kamera Flaş: Var\n- Batarya Kapasitesi Aralığı: 5000-6000 mAh\n- Yüz Tanıma: Var\n- Suya/Toza Dayanıklılık: Var\n- Ön Kamera Çözünürlüğü: 8 MP ve üstü\n- Dokunmatik Ekran: Var\n- Ön Kamera Flaş: Var\n- Şarj Hızı: 20-40 W\n- Şarj Girişi: USB Type-C\n- Ekran Çözünürlüğü: FHD+\n- Ekran Cinsi: Super AMOLED\n- Ekran Boyut Aralığı: 6.5'' - 7''\n- Ekran Yenileme Hızı: 120 Hz\n- Cep Telefonu Modeli: Samsung Galaxy A26\n- Ön Kamera Sayısı: 1\n- Ön Kamera Çözünürlük Aralığı: 15 - 20 MP\n- Görüntü Teknolojisi: AMOLED\n- Arka Kamera Sayısı: 1\n- İşletim Sistemi: Android\n- Çift Hat: Var\n- Kablosuz Şarj: Yok\n- Garanti Süresi: 2 Yıl\n- Ana Kamera Çözünürlük Aralığı: 40 - 60 MP\n- Renk: Siyah\n- NFC: Var\n- Video Kayıt Çözünürlüğü: 2160p (Ultra HD) 4K\n- Arttırılabilir Hafıza (Hafıza Kartı Desteği): Var\n- Parmak İzi Okuyucu: Var\n- Yapay Zeka: Var\n- Özellik: Kablosuz\n\nEk Bilgiler:\n- Kargo: kargonun bedava\n- İade Koşulu: 15 gün içinde ücretsiz iade\n- Barkod No: 8806097100621",
        "rating": 4.542347696879643,
        "reviews_count": 673,
        "stock": 10,
        "brand": "Samsung Galaxy A26 5G 256 GB Akıllı Telefon Siyah (Samsung Türkiye Garantili)",
        "category": "Trendyol",
        "subcategory": "Samsung > Elektronik > Telefon > Cep Telefonu > Android Cep Telefonu > Samsung Android Cep Telefonu > Elektronik > Telefon > Cep Telefonu > Android Cep Telefonu > Samsung Android Cep Telefonu > Samsung Galaxy A26 5G 256 GB Akıllı Telefon Siyah (Samsung Türkiye Garantili)",
        "attributes": {
            "Ekran Boyutu": "6,7 inç",
            "Dahili Hafıza": "256 GB",
            "Garanti Tipi": "Resmi Distribütör Garantili",
            "Kamera Çözünürlüğü": "20 MP ve üstü",
            "RAM Kapasitesi": "6 GB",
            "Pil Gücü (mAh)": "5000 ve üstü",
            "Mobil Bağlantı Hızı": "4.5G",
            "Ekran Teknolojisi": "Dinamik AMOLED",
            "Kulaklık Girişi": "3.5 mm",
            "Ana Kamera Flaş": "Var",
            "Batarya Kapasitesi Aralığı": "5000-6000 mAh",
            "Yüz Tanıma": "Var",
            "Suya/Toza Dayanıklılık": "Var",
            "Ön Kamera Çözünürlüğü": "8 MP ve üstü",
            "Dokunmatik Ekran": "Var",
            "Ön Kamera Flaş": "Var",
            "Şarj Hızı": "20-40 W",
            "Şarj Girişi": "USB Type-C",
            "Ekran Çözünürlüğü": "FHD+",
            "Ekran Cinsi": "Super AMOLED",
            "Ekran Boyut Aralığı": "6.5'' - 7''",
            "Ekran Yenileme Hızı": "120 Hz",
            "Cep Telefonu Modeli": "Samsung Galaxy A26",
            "Ön Kamera Sayısı": "1",
            "Ön Kamera Çözünürlük Aralığı": "15 - 20 MP",
            "Görüntü Teknolojisi": "AMOLED",
            "Arka Kamera Sayısı": "1",
            "İşletim Sistemi": "Android",
            "Çift Hat": "Var",
            "Kablosuz Şarj": "Yok",
            "Garanti Süresi": "2 Yıl",
            "Ana Kamera Çözünürlük Aralığı": "40 - 60 MP",
            "Renk": "Siyah",
            "NFC": "Var",
            "Video Kayıt Çözünürlüğü": "2160p (Ultra HD) 4K",
            "Arttırılabilir Hafıza (Hafıza Kartı Desteği)": "Var",
            "Parmak İzi Okuyucu": "Var",
            "Yapay Zeka": "Var",
            "Özellik": "Kablosuz"
        },
        "additional_info": {
            "Kargo": "kargonun bedava",
            "İade Koşulu": "15 gün içinde ücretsiz iade",
            "Barkod No": "8806097100621"
        }
    },
    {
        "platform": "trendyol",
        "external_id": "66856442",
        "title": "Samsung MS23K3515AS 23 Litre Mikrodalga Fırın - Gri MS23K3515AS 23 Litre Mikrodalga Fırın - Gri",
        "price": 5500.0,
        "currency": "TRY",
        "image_url": "https://cdn.dsmcdn.com/mnresize/400/-/ty151/product/media/images/20210731/16/114380381/116387070/1/1_org_zoom.jpg",
        "image_urls": [
            "https://cdn.dsmcdn.com/mnresize/620/920/ty151/product/media/images/20210731/16/114380381/116387070/1/1_org_zoom.jpg",
            "https://cdn.dsmcdn.com/mnresize/620/920/ty152/product/media/images/20210731/16/114380381/116387070/2/2_org_zoom.jpg",
            "https://cdn.dsmcdn.com/mnresize/128/-/indexing-sticker-stamp/mars/bc279028-2fde-461a-80ba-df1c7e816910.png",
            "https://cdn.dsmcdn.com/mnresize/620/920/ty152/product/media/images/20210731/16/114380381/116387070/3/3_org_zoom.jpg",
            "https://cdn.dsmcdn.com/mnresize/-/49/ty925/product/inventory/vas/seller-logo-463180-trendyol-sigorta-1002.jpg",
            "https://cdn.dsmcdn.com/mnresize/-/49/ty922/product/inventory/vas/seller-logo-463180-trendyol-sigorta-1003.jpg",
            "https://cdn.dsmcdn.com/mnresize/-/49/ty925/product/inventory/vas/seller-logo-463180-trendyol-sigorta-1004.jpg",
            "https://cdn.dsmcdn.com/web/prod/fp/ai1_1744811068004.svg",
            "https://cdn.dsmcdn.com/web/prod/fp/info_1744805921885.svg",
            "https://cdn.dsmcdn.com/web/production/placeholder-card.svg"
        ],
        "product_url": "https://www.trendyol.com/samsung/ms23k3515as-23-litre-mikrodalga-firin-gri-p-66856442?boutiqueId=61&merchantId=275331",
        "description": "Bu ürün \nMediaMarkt\n tarafından gönderilecektir.\nKampanya fiyatından satılmak üzere 100 adetten fazla stok sunulmuştur.\nİncelemiş olduğunuz ürünün satış fiyatını satıcı belirlemektedir.\nBir ürün, birden fazla satıcı tarafından satılabilir. Birden fazla satıcı tarafından satışa sunulan ürünlerin satıcıları ürün için belirledikleri fiyata, satıcı puanlarına, teslimat statülerine, ürünlerdeki promosyonlara, kargonun bedava olup olmamasına ve ürünlerin hızlı teslimat ile teslim edilip edilememesine, ürünlerin stok ve kategorileri bilgilerine göre sıralanmaktadır.\n\n...\n\nÜrün Özellikleri:\n- Garanti Tipi: Resmi Distribütör Garantili\n- Kontrol Tipi: Digital\n- Garanti Süresi: 2 Yıl\n- Hacim: 25 L\n- Renk: Gri\n- Güç: 1001 - 1250 W\n- Kullanım Şekli: Solo\n- Izgara Özelliği: Yok\n- Tema / Stil: Modern\n- Özellik: Diğer\n\nEk Bilgiler:\n- Kargo: kargonun bedava\n- İade Koşulu: 15 gün içinde ücretsiz iade\n- Barkod No: 8806090659010",
        "rating": 4.670687575392039,
        "reviews_count": 829,
        "stock": 10,
        "brand": "Samsung MS23K3515AS 23 Litre Mikrodalga Fırın - Gri",
        "category": "Trendyol",
        "subcategory": "Samsung > Elektronik > Beyaz Eşya > Mikrodalga Fırın > Samsung Mikrodalga Fırın > Elektronik > Beyaz Eşya > Mikrodalga Fırın > Samsung Mikrodalga Fırın > Samsung MS23K3515AS 23 Litre Mikrodalga Fırın - Gri",
        "attributes": {
            "Garanti Tipi": "Resmi Distribütör Garantili",
            "Kontrol Tipi": "Digital",
            "Garanti Süresi": "2 Yıl",
            "Hacim": "25 L",
            "Renk": "Gri",
            "Güç": "1001 - 1250 W",
            "Kullanım Şekli": "Solo",
            "Izgara Özelliği": "Yok",
            "Tema / Stil": "Modern",
            "Özellik": "Diğer"
        },
        "additional_info": {
            "Kargo": "kargonun bedava",
            "İade Koşulu": "15 gün içinde ücretsiz iade",
            "Barkod No": "8806090659010"
        }
    },
    {
        "platform": "trendyol",
        "external_id": "1106471722",
        "title": "Samsung Galaxy Buds4 Pro (ANC) Bluetooth Kulak İçi Kulaklık Siyah Galaxy Buds4 Pro (ANC) Bluetooth Kulak İçi Kulaklık Siyah",
        "price": 111085712325.17,
        "currency": "TRY",
        "image_url": "https://cdn.dsmcdn.com/mnresize/400/-/ty1842/prod/QC_ENRICHMENT/20260323/12/7477bb48-e587-3d10-9508-ac38f9fe82bd/1_org_zoom.jpg",
        "image_urls": [
            "https://cdn.dsmcdn.com/mnresize/620/920/ty1842/prod/QC_ENRICHMENT/20260323/12/7477bb48-e587-3d10-9508-ac38f9fe82bd/1_org_zoom.jpg",
            "https://cdn.dsmcdn.com/mnresize/128/-/indexing-sticker-stamp/mars/c2c6e24b-0c8f-4b13-9fb9-5e0a3aeb15a1.png",
            "https://cdn.dsmcdn.com/mnresize/128/-/indexing-sticker-stamp/mars/745f86fe-b3a5-4a78-a5d8-f8b0d36c6d3d.png",
            "https://cdn.dsmcdn.com/mnresize/-/49/ty925/product/inventory/vas/seller-logo-463180-trendyol-sigorta-1004.jpg",
            "https://cdn.dsmcdn.com/mnresize/-/49/ty922/product/inventory/vas/seller-logo-463180-trendyol-sigorta-1003.jpg",
            "https://cdn.dsmcdn.com/mnresize/-/49/ty925/product/inventory/vas/seller-logo-463180-trendyol-sigorta-1002.jpg",
            "https://cdn.dsmcdn.com/mnresize/-/49/ty925/product/inventory/vas/seller-logo-463180-trendyol-sigorta-1008.jpg",
            "https://cdn.dsmcdn.com/web/production/placeholder-card.svg"
        ],
        "product_url": "https://www.trendyol.com/samsung/galaxy-buds4-pro-anc-bluetooth-kulak-ici-kulaklik-siyah-p-1106471722?boutiqueId=689770&merchantId=968",
        "description": "Bu ürün \nTrendyol\n tarafından gönderilecektir.\nKampanya fiyatından satılmak üzere 50 adetten fazla stok sunulmuştur.\nÜrüne ait garanti belgesi ile tanıtma ve kullanım kılavuzları; kağıt ortamında paylaşılabileceği gibi elektronik ortamda erişim sağlayabileceğiniz, link ve karekod biçiminde de sunulabilecektir. Ürün teslimi sonrası ambalajın, paketin, kutunun dikkatle açılması tavsiye edilir.\nBir ürün, birden fazla satıcı tarafından satılabilir. Birden fazla satıcı tarafından satışa sunulan ürünlerin satıcıları ürün için belirledikleri fiyata, satıcı puanlarına, teslimat statülerine, ürünlerdeki promosyonlara, kargonun bedava olup olmamasına ve ürünlerin hızlı teslimat ile teslim edilip edilememesine, ürünlerin stok ve kategorileri bilgilerine göre sıralanmaktadır.\n\nÜrün Özellikleri:\n- Garanti Tipi: İthalatçı Garantili\n- Aktif Gürültü Önleme (ANC): Var\n- Dokunmatik Kontrol: Var\n- Renk: Siyah\n- Suya/Tere Dayanıklılık: Var\n- Mikrofon: Var\n- Bluetooth Versiyon: 6.0\n- Garanti Süresi: 2 Yıl\n- Çift Telefon Desteği: Var\n- Tamir Edilebilirlik: Yetkili Servis ile Tamiri Gerekir.",
        "rating": 4.733333333333333,
        "reviews_count": 15,
        "stock": 10,
        "brand": "Samsung Galaxy Buds4 Pro (ANC) Bluetooth Kulak İçi Kulaklık Siyah",
        "category": "Trendyol",
        "subcategory": "Samsung > Elektronik > Kulaklık > Bluetooth Kulaklık > Kulak İçi Bluetooth Kulaklık > Samsung Kulak İçi Bluetooth Kulaklık > Elektronik > Kulaklık > Bluetooth Kulaklık > Kulak İçi Bluetooth Kulaklık > Samsung Kulak İçi Bluetooth Kulaklık > Samsung Galaxy Buds4 Pro (ANC) Bluetooth Kulak İçi Kulaklık Siyah",
        "attributes": {
            "Garanti Tipi": "İthalatçı Garantili",
            "Aktif Gürültü Önleme (ANC)": "Var",
            "Dokunmatik Kontrol": "Var",
            "Renk": "Siyah",
            "Suya/Tere Dayanıklılık": "Var",
            "Mikrofon": "Var",
            "Bluetooth Versiyon": "6.0",
            "Garanti Süresi": "2 Yıl",
            "Çift Telefon Desteği": "Var",
            "Tamir Edilebilirlik": "Yetkili Servis ile Tamiri Gerekir."
        },
        "additional_info": null
    },
    {
        "platform": "trendyol",
        "external_id": "882761835",
        "title": "Samsung Galaxy A16 4 Gb Ram 128 Gb Gri Galaxy A16 4 Gb Ram 128 Gb Gri",
        "price": 9899.0,
        "currency": "TRY",
        "image_url": "https://cdn.dsmcdn.com/mnresize/400/-/ty1701/prod/QC_PREP/20250630/11/7d13f4da-a5d8-387e-a54a-81872248996f/1_org_zoom.jpg",
        "image_urls": [
            "https://cdn.dsmcdn.com/mnresize/620/920/ty1701/prod/QC_PREP/20250630/11/7d13f4da-a5d8-387e-a54a-81872248996f/1_org_zoom.jpg",
            "https://cdn.dsmcdn.com/mnresize/620/920/ty1719/prod/QC_ENRICHMENT/20250805/14/a9f7d337-1d17-3fad-bc6e-f8fb5484e94b/1_org_zoom.jpg",
            "https://cdn.dsmcdn.com/mnresize/128/-/indexing-sticker-stamp/mars/bc279028-2fde-461a-80ba-df1c7e816910.png",
            "https://cdn.dsmcdn.com/mnresize/620/920/ty1721/prod/QC_ENRICHMENT/20250805/14/eb9eb77a-2871-3e02-bd2a-ab21bd5d2073/1_org_zoom.jpg",
            "https://cdn.dsmcdn.com/mnresize/620/920/ty1720/prod/QC_ENRICHMENT/20250805/14/5d0b0441-fa9f-394d-8e3a-e63b20442f75/1_org_zoom.jpg",
            "https://cdn.dsmcdn.com/mnresize/620/920/ty1719/prod/QC_ENRICHMENT/20250805/14/a4932b25-da82-373c-aab3-065a1a7ad15b/1_org_zoom.jpg",
            "https://cdn.dsmcdn.com/mnresize/620/920/ty1719/prod/QC_ENRICHMENT/20250805/14/21a62299-c3c7-3675-8ed3-99f8a2334d1f/1_org_zoom.jpg",
            "https://cdn.dsmcdn.com/mnresize/620/920/ty1720/prod/QC_ENRICHMENT/20250805/14/f5d9807b-ba7d-33e5-a339-dc6aeda41d99/1_org_zoom.jpg",
            "https://cdn.dsmcdn.com/mnresize/620/920/ty1720/prod/QC_ENRICHMENT/20250805/14/e1565bfa-d4d5-346f-a63c-96199fedcbf1/1_org_zoom.jpg",
            "https://cdn.dsmcdn.com/mnresize/-/49/ty925/product/inventory/vas/seller-logo-463180-trendyol-sigorta-1002.jpg",
            "https://cdn.dsmcdn.com/mnresize/-/49/ty924/product/inventory/vas/seller-logo-463180-trendyol-sigorta-1001.jpg",
            "https://cdn.dsmcdn.com/mnresize/-/49/ty925/product/inventory/vas/seller-logo-463180-trendyol-sigorta-1008.jpg",
            "https://cdn.dsmcdn.com/web/prod/fp/ai1_1744811068004.svg",
            "https://cdn.dsmcdn.com/web/prod/fp/info_1744805921885.svg",
            "https://cdn.dsmcdn.com/web/production/placeholder-card.svg"
        ],
        "product_url": "https://www.trendyol.com/samsung/galaxy-a16-4-gb-ram-128-gb-gri-p-882761835?boutiqueId=689770&merchantId=968",
        "description": "Bu ürün \nTrendyol\n tarafından gönderilecektir.\nKampanya fiyatından satılmak üzere 100 adetten fazla stok sunulmuştur.\nİncelemiş olduğunuz ürünün satış fiyatını satıcı belirlemektedir.\nÜrüne ait garanti belgesi ile tanıtma ve kullanım kılavuzları; kağıt ortamında paylaşılabileceği gibi elektronik ortamda erişim sağlayabileceğiniz, link ve karekod biçiminde de sunulabilecektir. Ürün teslimi sonrası ambalajın, paketin, kutunun dikkatle açılması tavsiye edilir.\n\n...\n\nÜrün Özellikleri:\n- Ön Kamera Çözünürlüğü: 13 MP\n- Ekran Boyutu: 6,8 inç\n- Dahili Hafıza: 128 GB\n- Garanti Tipi: Samsung TR Garantili\n- Kamera Çözünürlüğü: 20 MP ve üstü\n- RAM Kapasitesi: 4 GB\n- Pil Gücü (mAh): 5000\n- Mobil Bağlantı Hızı: 4.5G\n- Yüz Tanıma: Var\n- Ekran Teknolojisi: FHD+\n- Batarya Kapasitesi Aralığı: 5000-6000 mAh\n- Kulaklık Girişi: USB Type-C\n- Suya/Toza Dayanıklılık: Var\n- Ana Kamera Flaş: Var\n- Dokunmatik Ekran: Var\n- Ön Kamera Flaş: Yok\n- Şarj Hızı: 10-20 W\n- Şarj Girişi: USB Type-C\n- Ekran Çözünürlüğü: FHD+\n- Ekran Cinsi: LCD\n- Ekran Boyut Aralığı: 6.5'' - 7''\n- Ekran Yenileme Hızı: 60 Hz\n- Cep Telefonu Modeli: Samsung Galaxy A16\n- Ön Kamera Sayısı: 1\n- Ön Kamera Çözünürlük Aralığı: 10 - 15 MP\n- Görüntü Teknolojisi: AMOLED\n- Arka Kamera Sayısı: 3\n- İşletim Sistemi: Android\n- Çift Hat: Var\n- Kablosuz Şarj: Yok\n- Garanti Süresi: 2 Yıl\n- Ana Kamera Çözünürlük Aralığı: 40 - 60 MP\n- Renk: Gri\n- NFC: Var\n- Video Kayıt Çözünürlüğü: 1080p (Full HD)\n- Arttırılabilir Hafıza (Hafıza Kartı Desteği): Var\n- Parmak İzi Okuyucu: Var\n- Yapay Zeka: Var\n- Tamir Edilebilirlik: Yetkili Servis ile Tamiri Gerekir.\n- Özellik: Kablosuz",
        "rating": 4.492156862745098,
        "reviews_count": 510,
        "stock": 10,
        "brand": "Samsung Galaxy A16 4 Gb Ram 128 Gb Gri",
        "category": "Trendyol",
        "subcategory": "Samsung > Elektronik > Telefon > Cep Telefonu > Android Cep Telefonu > Samsung Android Cep Telefonu > Elektronik > Telefon > Cep Telefonu > Android Cep Telefonu > Samsung Android Cep Telefonu > Samsung Galaxy A16 4 Gb Ram 128 Gb Gri",
        "attributes": {
            "Ön Kamera Çözünürlüğü": "13 MP",
            "Ekran Boyutu": "6,8 inç",
            "Dahili Hafıza": "128 GB",
            "Garanti Tipi": "Samsung TR Garantili",
            "Kamera Çözünürlüğü": "20 MP ve üstü",
            "RAM Kapasitesi": "4 GB",
            "Pil Gücü (mAh)": "5000",
            "Mobil Bağlantı Hızı": "4.5G",
            "Yüz Tanıma": "Var",
            "Ekran Teknolojisi": "FHD+",
            "Batarya Kapasitesi Aralığı": "5000-6000 mAh",
            "Kulaklık Girişi": "USB Type-C",
            "Suya/Toza Dayanıklılık": "Var",
            "Ana Kamera Flaş": "Var",
            "Dokunmatik Ekran": "Var",
            "Ön Kamera Flaş": "Yok",
            "Şarj Hızı": "10-20 W",
            "Şarj Girişi": "USB Type-C",
            "Ekran Çözünürlüğü": "FHD+",
            "Ekran Cinsi": "LCD",
            "Ekran Boyut Aralığı": "6.5'' - 7''",
            "Ekran Yenileme Hızı": "60 Hz",
            "Cep Telefonu Modeli": "Samsung Galaxy A16",
            "Ön Kamera Sayısı": "1",
            "Ön Kamera Çözünürlük Aralığı": "10 - 15 MP",
            "Görüntü Teknolojisi": "AMOLED",
            "Arka Kamera Sayısı": "3",
            "İşletim Sistemi": "Android",
            "Çift Hat": "Var",
            "Kablosuz Şarj": "Yok",
            "Garanti Süresi": "2 Yıl",
            "Ana Kamera Çözünürlük Aralığı": "40 - 60 MP",
            "Renk": "Gri",
            "NFC": "Var",
            "Video Kayıt Çözünürlüğü": "1080p (Full HD)",
            "Arttırılabilir Hafıza (Hafıza Kartı Desteği)": "Var",
            "Parmak İzi Okuyucu": "Var",
            "Yapay Zeka": "Var",
            "Tamir Edilebilirlik": "Yetkili Servis ile Tamiri Gerekir.",
            "Özellik": "Kablosuz"
        },
        "additional_info": null
    },
    {
        "platform": "trendyol",
        "external_id": "978670800",
        "title": "Samsung Galaxy Tab S10 Lite 6GB 128GB Mercan Tablet Galaxy Tab S10 Lite 6GB 128GB Mercan Tablet",
        "price": 12849.14,
        "currency": "TRY",
        "image_url": "https://cdn.dsmcdn.com/mnresize/400/-/ty1848/prod/QC_ENRICHMENT/20260403/17/393c3556-7197-3d87-90c5-532c586f120e/1_org_zoom.jpg",
        "image_urls": [
            "https://cdn.dsmcdn.com/mnresize/620/920/ty1848/prod/QC_ENRICHMENT/20260403/17/393c3556-7197-3d87-90c5-532c586f120e/1_org_zoom.jpg",
            "https://cdn.dsmcdn.com/mnresize/620/920/ty1850/prod/QC_ENRICHMENT/20260403/17/36572a52-38e5-37b0-a513-3aa39e07a6e7/1_org_zoom.jpg",
            "https://cdn.dsmcdn.com/mnresize/128/-/indexing-sticker-stamp/mars/5cccd9b0-5c0f-43e8-b839-1fd1dec48740.png",
            "https://cdn.dsmcdn.com/mnresize/128/-/indexing-sticker-stamp/mars/745f86fe-b3a5-4a78-a5d8-f8b0d36c6d3d.png",
            "https://cdn.dsmcdn.com/mnresize/620/920/ty1848/prod/QC_ENRICHMENT/20260403/17/f846a54a-8b52-36ee-a171-895448b41b49/1_org_zoom.jpg",
            "https://cdn.dsmcdn.com/mnresize/620/920/ty1849/prod/QC_ENRICHMENT/20260403/17/d71b4e2b-7779-3f30-bb8c-c2e8ab6547ce/1_org_zoom.jpg",
            "https://cdn.dsmcdn.com/mnresize/620/920/ty1849/prod/QC_ENRICHMENT/20260403/17/e3c2128a-b93d-3c8d-8d07-46b44b070b83/1_org_zoom.jpg",
            "https://cdn.dsmcdn.com/mnresize/620/920/ty1850/prod/QC_ENRICHMENT/20260403/17/2ac84e37-f4a8-3b35-b6cc-e2b6180fa6ce/1_org_zoom.jpg",
            "https://cdn.dsmcdn.com/mnresize/620/920/ty1850/prod/QC_ENRICHMENT/20260403/17/b6200e4c-852f-3c89-a7b4-d632763742dd/1_org_zoom.jpg",
            "https://cdn.dsmcdn.com/mnresize/620/920/ty1850/prod/QC_ENRICHMENT/20260403/17/2d63c5ff-b5e5-3270-a3f0-fd786d993422/1_org_zoom.jpg",
            "https://cdn.dsmcdn.com/mnresize/-/49/ty925/product/inventory/vas/seller-logo-463180-trendyol-sigorta-1002.jpg",
            "https://cdn.dsmcdn.com/mnresize/-/49/ty924/product/inventory/vas/seller-logo-463180-trendyol-sigorta-1001.jpg",
            "https://cdn.dsmcdn.com/mnresize/-/49/ty925/product/inventory/vas/seller-logo-463180-trendyol-sigorta-1008.jpg",
            "https://cdn.dsmcdn.com/web/prod/fp/ai1_1744811068004.svg",
            "https://cdn.dsmcdn.com/web/prod/fp/info_1744805921885.svg",
            "https://cdn.dsmcdn.com/web/production/placeholder-card.svg"
        ],
        "product_url": "https://www.trendyol.com/samsung/galaxy-tab-s10-lite-6gb-128gb-mercan-tablet-p-978670800?boutiqueId=689770&merchantId=968",
        "description": "Bu ürün \nTrendyol\n tarafından gönderilecektir.\nKampanya fiyatından satılmak üzere 100 adetten fazla stok sunulmuştur.\nİncelemiş olduğunuz ürünün satış fiyatını satıcı belirlemektedir.\nÜrüne ait garanti belgesi ile tanıtma ve kullanım kılavuzları; kağıt ortamında paylaşılabileceği gibi elektronik ortamda erişim sağlayabileceğiniz, link ve karekod biçiminde de sunulabilecektir. Ürün teslimi sonrası ambalajın, paketin, kutunun dikkatle açılması tavsiye edilir.\n\nÜrün Özellikleri:\n- Kapasite: 128 GB\n- Çözünürlük: 3840 x 2160\n- Garanti Tipi: Samsung TR Garantili\n- Bluetooth: Var\n- Kamera Çözünürlüğü: 5 MP ve altı\n- İşletim Sistemi: Android\n- Bellek Kapasitesi: 4 - 16 GB\n- Renk: Kırmızı\n- Sim Kart Uyumu: Yok\n- Bağlantılar: USB-C\n- İşlemci Çekirdek Sayısı: 8\n- İşlemci Tipi: Samsung\n- Ekran Boyutu: 10,7 inç\n- Ram (Sistem Belleği): 6 GB\n- Görüntüleme Teknolojisi: TFT\n- Garanti Süresi: 2 Yıl\n- HDMI: Yok\n- Hızlı Şarj: Var\n- Tamir Edilebilirlik: Yetkili Servis ile Tamiri Gerekir.\n- Özellik: Diğer",
        "rating": 4.588235294117647,
        "reviews_count": 239,
        "stock": 10,
        "brand": "Samsung Galaxy Tab S10 Lite 6GB 128GB Mercan Tablet",
        "category": "Trendyol",
        "subcategory": "Samsung > Elektronik > Bilgisayar&Tablet > Tablet Grubu > Tablet > Samsung Tablet > Elektronik > Bilgisayar&Tablet > Tablet Grubu > Tablet > Samsung Tablet > Samsung Galaxy Tab S10 Lite 6GB 128GB Mercan Tablet",
        "attributes": {
            "Kapasite": "128 GB",
            "Çözünürlük": "3840 x 2160",
            "Garanti Tipi": "Samsung TR Garantili",
            "Bluetooth": "Var",
            "Kamera Çözünürlüğü": "5 MP ve altı",
            "İşletim Sistemi": "Android",
            "Bellek Kapasitesi": "4 - 16 GB",
            "Renk": "Kırmızı",
            "Sim Kart Uyumu": "Yok",
            "Bağlantılar": "USB-C",
            "İşlemci Çekirdek Sayısı": "8",
            "İşlemci Tipi": "Samsung",
            "Ekran Boyutu": "10,7 inç",
            "Ram (Sistem Belleği)": "6 GB",
            "Görüntüleme Teknolojisi": "TFT",
            "Garanti Süresi": "2 Yıl",
            "HDMI": "Yok",
            "Hızlı Şarj": "Var",
            "Tamir Edilebilirlik": "Yetkili Servis ile Tamiri Gerekir.",
            "Özellik": "Diğer"
        },
        "additional_info": null
    },
    {
        "platform": "trendyol",
        "external_id": "978670936",
        "title": "Samsung Galaxy Tab S11 12GB 128GB Gri Tablet Galaxy Tab S11 12GB 128GB Gri Tablet",
        "price": 28810.7729767,
        "currency": "TRY",
        "image_url": "https://cdn.dsmcdn.com/mnresize/400/-/ty1743/product/media/images/prod/PIM/20250903/14/dea3a6dc-0e56-4a4c-9535-e4db115f59dc/1_org_zoom.jpg",
        "image_urls": [
            "https://cdn.dsmcdn.com/mnresize/620/920/ty1743/product/media/images/prod/PIM/20250903/14/dea3a6dc-0e56-4a4c-9535-e4db115f59dc/1_org_zoom.jpg",
            "https://cdn.dsmcdn.com/mnresize/620/920/ty1745/product/media/images/prod/PIM/20250903/14/e0f24f7a-8739-4a02-a4a6-a5483be06704/1_org_zoom.jpg",
            "https://cdn.dsmcdn.com/mnresize/128/-/indexing-sticker-stamp/mars/8f774b22-6554-41f4-9ccc-35f0b1f48d60.png",
            "https://cdn.dsmcdn.com/mnresize/128/-/indexing-sticker-stamp/mars/82397e3f-ef16-4c1b-80b2-91c6c167011c.png",
            "https://cdn.dsmcdn.com/mnresize/620/920/ty1744/product/media/images/prod/PIM/20250903/14/22bce1cb-0223-469e-bd6c-9dc6530d6b90/1_org_zoom.jpg",
            "https://cdn.dsmcdn.com/mnresize/620/920/ty1740/product/media/images/prod/PIM/20250903/14/a8b7c1ef-3aa8-4e20-a3bd-b682a41d1e16/1_org_zoom.jpg",
            "https://cdn.dsmcdn.com/mnresize/620/920/ty1741/product/media/images/prod/PIM/20250903/14/d8063851-db2c-48b9-938a-973df9b97e41/1_org_zoom.jpg",
            "https://cdn.dsmcdn.com/mnresize/620/920/ty1743/product/media/images/prod/PIM/20250903/14/aa279e79-b9b6-4615-8df8-c22cfa3d17bd/1_org_zoom.jpg",
            "https://cdn.dsmcdn.com/mnresize/620/920/ty1743/product/media/images/prod/PIM/20250903/14/e53fb30a-0991-4dd1-991a-e588544c53f0/1_org_zoom.jpg",
            "https://cdn.dsmcdn.com/mnresize/620/920/ty1743/product/media/images/prod/PIM/20250903/14/8a2879e8-caba-4503-a490-2ff7972f4536/1_org_zoom.jpg",
            "https://cdn.dsmcdn.com/mnresize/620/920/ty1745/product/media/images/prod/PIM/20250903/14/58f1eb27-595d-48ff-979b-df71be29fe6d/1_org_zoom.jpg",
            "https://cdn.dsmcdn.com/mnresize/620/920/ty1743/product/media/images/prod/PIM/20250903/14/213750d6-ee1d-47b7-810f-7de27cbf0f5c/1_org_zoom.jpg",
            "https://cdn.dsmcdn.com/mnresize/620/920/ty1745/product/media/images/prod/PIM/20250903/14/ceac2f55-5518-4967-99d8-d7d40c6070a9/1_org_zoom.jpg",
            "https://cdn.dsmcdn.com/mnresize/620/920/ty1744/product/media/images/prod/PIM/20250903/14/1920d987-1f45-4fc9-b831-03facd82d7a1/1_org_zoom.jpg",
            "https://cdn.dsmcdn.com/mnresize/620/920/ty1742/product/media/images/prod/PIM/20250903/14/ff759522-5518-47dd-ab2c-0fbe6a285ec7/1_org_zoom.jpg",
            "https://cdn.dsmcdn.com/mnresize/-/49/ty925/product/inventory/vas/seller-logo-463180-trendyol-sigorta-1002.jpg",
            "https://cdn.dsmcdn.com/mnresize/-/49/ty924/product/inventory/vas/seller-logo-463180-trendyol-sigorta-1001.jpg",
            "https://cdn.dsmcdn.com/mnresize/-/49/ty925/product/inventory/vas/seller-logo-463180-trendyol-sigorta-1008.jpg",
            "https://cdn.dsmcdn.com/web/production/placeholder-card.svg"
        ],
        "product_url": "https://www.trendyol.com/samsung/galaxy-tab-s11-12gb-128gb-gri-tablet-p-978670936?boutiqueId=689770&merchantId=968",
        "description": "Bu ürün \nTrendyol\n tarafından gönderilecektir.\nKampanya fiyatından satılmak üzere 100 adetten fazla stok sunulmuştur.\nİncelemiş olduğunuz ürünün satış fiyatını satıcı belirlemektedir.\nÜrüne ait garanti belgesi ile tanıtma ve kullanım kılavuzları; kağıt ortamında paylaşılabileceği gibi elektronik ortamda erişim sağlayabileceğiniz, link ve karekod biçiminde de sunulabilecektir. Ürün teslimi sonrası ambalajın, paketin, kutunun dikkatle açılması tavsiye edilir.\n\nÜrün Özellikleri:\n- Kapasite: 128 GB\n- Çözünürlük: 3840 x 2160\n- Ekran Boyutu: 11 inç\n- Kamera Çözünürlüğü: 10 - 15 MP\n- Garanti Tipi: Samsung TR Garantili\n- Bluetooth: Var\n- İşletim Sistemi: Android\n- Bellek Kapasitesi: 4 - 16 GB\n- Renk: Gri\n- Sim Kart Uyumu: Yok\n- Bağlantılar: USB-C\n- İşlemci Çekirdek Sayısı: 8\n- İşlemci Tipi: MediaTek\n- Ram (Sistem Belleği): 12 GB\n- Görüntüleme Teknolojisi: Dynamic Amoled 2X\n- Garanti Süresi: 2 Yıl\n- HDMI: Yok\n- Hızlı Şarj: Var\n- Tamir Edilebilirlik: Yetkili Servis ile Tamiri Gerekir.\n- Özellik: Kameralı\n\nEk Bilgiler:\n- Kargo: kargonun bedava\n- İade Koşulu: 15 gün içinde ücretsiz iade\n- Barkod No: 8806097716280",
        "rating": 4.44,
        "reviews_count": 25,
        "stock": 10,
        "brand": "Samsung Galaxy Tab S11 12GB 128GB Gri Tablet",
        "category": "Trendyol",
        "subcategory": "Samsung > Elektronik > Bilgisayar&Tablet > Tablet Grubu > Tablet > Samsung Tablet > Elektronik > Bilgisayar&Tablet > Tablet Grubu > Tablet > Samsung Tablet > Samsung Galaxy Tab S11 12GB 128GB Gri Tablet",
        "attributes": {
            "Kapasite": "128 GB",
            "Çözünürlük": "3840 x 2160",
            "Ekran Boyutu": "11 inç",
            "Kamera Çözünürlüğü": "10 - 15 MP",
            "Garanti Tipi": "Samsung TR Garantili",
            "Bluetooth": "Var",
            "İşletim Sistemi": "Android",
            "Bellek Kapasitesi": "4 - 16 GB",
            "Renk": "Gri",
            "Sim Kart Uyumu": "Yok",
            "Bağlantılar": "USB-C",
            "İşlemci Çekirdek Sayısı": "8",
            "İşlemci Tipi": "MediaTek",
            "Ram (Sistem Belleği)": "12 GB",
            "Görüntüleme Teknolojisi": "Dynamic Amoled 2X",
            "Garanti Süresi": "2 Yıl",
            "HDMI": "Yok",
            "Hızlı Şarj": "Var",
            "Tamir Edilebilirlik": "Yetkili Servis ile Tamiri Gerekir.",
            "Özellik": "Kameralı"
        },
        "additional_info": {
            "Kargo": "kargonun bedava",
            "İade Koşulu": "15 gün içinde ücretsiz iade",
            "Barkod No": "8806097716280"
        }
    },
    {
        "platform": "trendyol",
        "external_id": "917839731",
        "title": "Samsung Galaxy A56 5G 8 GB RAM 256 GB Gri Galaxy A56 5G 8 GB RAM 256 GB Gri",
        "price": 2379924898.09,
        "currency": "TRY",
        "image_url": "https://cdn.dsmcdn.com/mnresize/400/-/ty1817/prod/QC_ENRICHMENT/20260128/18/6f9a22ec-884e-32ca-918b-5a2824be272a/1_org_zoom.jpg",
        "image_urls": [
            "https://cdn.dsmcdn.com/mnresize/620/920/ty1817/prod/QC_ENRICHMENT/20260128/18/6f9a22ec-884e-32ca-918b-5a2824be272a/1_org_zoom.jpg",
            "https://cdn.dsmcdn.com/mnresize/128/-/indexing-sticker-stamp/mars/81901534-f3f6-4495-8d32-d2bcc648ec11.png",
            "https://cdn.dsmcdn.com/mnresize/128/-/indexing-sticker-stamp/mars/bc279028-2fde-461a-80ba-df1c7e816910.png",
            "https://cdn.dsmcdn.com/mnresize/-/49/ty925/product/inventory/vas/seller-logo-463180-trendyol-sigorta-1002.jpg",
            "https://cdn.dsmcdn.com/mnresize/-/49/ty924/product/inventory/vas/seller-logo-463180-trendyol-sigorta-1001.jpg",
            "https://cdn.dsmcdn.com/mnresize/-/49/ty925/product/inventory/vas/seller-logo-463180-trendyol-sigorta-1008.jpg",
            "https://cdn.dsmcdn.com/web/prod/fp/ai1_1744811068004.svg",
            "https://cdn.dsmcdn.com/web/prod/fp/info_1744805921885.svg",
            "https://cdn.dsmcdn.com/web/production/placeholder-card.svg"
        ],
        "product_url": "https://www.trendyol.com/samsung/galaxy-a56-5g-8-gb-ram-256-gb-gri-p-917839731?boutiqueId=689770&merchantId=968",
        "description": "Bu ürün \nTrendyol\n tarafından gönderilecektir.\nKampanya fiyatından satılmak üzere 100 adetten fazla stok sunulmuştur.\nİncelemiş olduğunuz ürünün satış fiyatını satıcı belirlemektedir.\nÜrüne ait garanti belgesi ile tanıtma ve kullanım kılavuzları; kağıt ortamında paylaşılabileceği gibi elektronik ortamda erişim sağlayabileceğiniz, link ve karekod biçiminde de sunulabilecektir. Ürün teslimi sonrası ambalajın, paketin, kutunun dikkatle açılması tavsiye edilir.\n\nÜrün Özellikleri:\n- Ön Kamera Çözünürlüğü: 12 MP\n- Dahili Hafıza: 256 GB\n- Ekran Boyutu: 6,7 inç\n- Garanti Tipi: Samsung TR Garantili\n- Kamera Çözünürlüğü: 50 MP + 12 MP + 5 MP\n- RAM Kapasitesi: 8 GB\n- Pil Gücü (mAh): 5000 ve üstü\n- Mobil Bağlantı Hızı: 5G\n- Kulaklık Girişi: USB Type-C\n- Ekran Teknolojisi: FHD+\n- Ana Kamera Flaş: Var\n- Yüz Tanıma: Var\n- Batarya Kapasitesi Aralığı: 5000-6000 mAh\n- Suya/Toza Dayanıklılık: Var\n- Dokunmatik Ekran: Var\n- Ön Kamera Flaş: Yok\n- Şarj Hızı: 40-60 W\n- Şarj Girişi: USB Type-C\n- Ekran Çözünürlüğü: FHD+\n- Ekran Cinsi: Super AMOLED\n- Ekran Boyut Aralığı: 6.5'' - 7''\n- Ekran Yenileme Hızı: 120 Hz\n- Cep Telefonu Modeli: Samsung Galaxy A56\n- Ön Kamera Sayısı: 1\n- Ön Kamera Çözünürlük Aralığı: 10 - 15 MP\n- Görüntü Teknolojisi: AMOLED\n- Arka Kamera Sayısı: 3\n- İşletim Sistemi: Android\n- Çift Hat: Var\n- Kablosuz Şarj: Yok\n- Garanti Süresi: 2 Yıl\n- Ana Kamera Çözünürlük Aralığı: 40 - 60 MP\n- Renk: Gri\n- NFC: Var\n- Video Kayıt Çözünürlüğü: 2160p (Ultra HD) 4K\n- Arttırılabilir Hafıza (Hafıza Kartı Desteği): Yok\n- Parmak İzi Okuyucu: Var\n- Yapay Zeka: Yok\n- Özellik: Otomatik\n\nEk Bilgiler:\n- Kargo: kargonun bedava\n- İade Koşulu: 15 gün içinde ücretsiz iade\n- Barkod No: 8806097054078",
        "rating": 4.6829629629629625,
        "reviews_count": 676,
        "stock": 10,
        "brand": "Samsung Galaxy A56 5G 8 GB RAM 256 GB Gri",
        "category": "Trendyol",
        "subcategory": "Samsung > Elektronik > Telefon > Cep Telefonu > Android Cep Telefonu > Samsung Android Cep Telefonu > Elektronik > Telefon > Cep Telefonu > Android Cep Telefonu > Samsung Android Cep Telefonu > Samsung Galaxy A56 5G 8 GB RAM 256 GB Gri",
        "attributes": {
            "Ön Kamera Çözünürlüğü": "12 MP",
            "Dahili Hafıza": "256 GB",
            "Ekran Boyutu": "6,7 inç",
            "Garanti Tipi": "Samsung TR Garantili",
            "Kamera Çözünürlüğü": "50 MP + 12 MP + 5 MP",
            "RAM Kapasitesi": "8 GB",
            "Pil Gücü (mAh)": "5000 ve üstü",
            "Mobil Bağlantı Hızı": "5G",
            "Kulaklık Girişi": "USB Type-C",
            "Ekran Teknolojisi": "FHD+",
            "Ana Kamera Flaş": "Var",
            "Yüz Tanıma": "Var",
            "Batarya Kapasitesi Aralığı": "5000-6000 mAh",
            "Suya/Toza Dayanıklılık": "Var",
            "Dokunmatik Ekran": "Var",
            "Ön Kamera Flaş": "Yok",
            "Şarj Hızı": "40-60 W",
            "Şarj Girişi": "USB Type-C",
            "Ekran Çözünürlüğü": "FHD+",
            "Ekran Cinsi": "Super AMOLED",
            "Ekran Boyut Aralığı": "6.5'' - 7''",
            "Ekran Yenileme Hızı": "120 Hz",
            "Cep Telefonu Modeli": "Samsung Galaxy A56",
            "Ön Kamera Sayısı": "1",
            "Ön Kamera Çözünürlük Aralığı": "10 - 15 MP",
            "Görüntü Teknolojisi": "AMOLED",
            "Arka Kamera Sayısı": "3",
            "İşletim Sistemi": "Android",
            "Çift Hat": "Var",
            "Kablosuz Şarj": "Yok",
            "Garanti Süresi": "2 Yıl",
            "Ana Kamera Çözünürlük Aralığı": "40 - 60 MP",
            "Renk": "Gri",
            "NFC": "Var",
            "Video Kayıt Çözünürlüğü": "2160p (Ultra HD) 4K",
            "Arttırılabilir Hafıza (Hafıza Kartı Desteği)": "Yok",
            "Parmak İzi Okuyucu": "Var",
            "Yapay Zeka": "Yok",
            "Özellik": "Otomatik"
        },
        "additional_info": {
            "Kargo": "kargonun bedava",
            "İade Koşulu": "15 gün içinde ücretsiz iade",
            "Barkod No": "8806097054078"
        }
    },
    {
        "platform": "trendyol",
        "external_id": "924102587",
        "title": "Samsung Galaxy Tab S10 FE 128 GB 10.9\" Mavi Tablet Galaxy Tab S10 FE 128 GB 10.9\" Mavi Tablet",
        "price": 17524.2917769,
        "currency": "TRY",
        "image_url": "https://cdn.dsmcdn.com/mnresize/400/-/ty1660/product/media/images/prod/PIM/20250408/14/f674f2a6-57f5-453f-938e-532146841671/1_org_zoom.jpg",
        "image_urls": [
            "https://cdn.dsmcdn.com/mnresize/620/920/ty1660/product/media/images/prod/PIM/20250408/14/f674f2a6-57f5-453f-938e-532146841671/1_org_zoom.jpg",
            "https://cdn.dsmcdn.com/mnresize/620/920/ty1660/product/media/images/prod/PIM/20250409/12/9371e7a3-f392-459f-a405-63a6a2670659/1_org_zoom.jpg",
            "https://cdn.dsmcdn.com/mnresize/128/-/indexing-sticker-stamp/mars/81901534-f3f6-4495-8d32-d2bcc648ec11.png",
            "https://cdn.dsmcdn.com/mnresize/128/-/indexing-sticker-stamp/mars/82397e3f-ef16-4c1b-80b2-91c6c167011c.png",
            "https://cdn.dsmcdn.com/mnresize/620/920/ty1659/product/media/images/prod/PIM/20250409/12/06ce1162-ee0e-40da-9b0a-d0552ada2c30/1_org_zoom.jpg",
            "https://cdn.dsmcdn.com/mnresize/620/920/ty1659/product/media/images/prod/PIM/20250409/12/379bf54b-3740-4be5-bfa1-00e7a87eee55/1_org_zoom.jpg",
            "https://cdn.dsmcdn.com/mnresize/620/920/ty1659/product/media/images/prod/PIM/20250409/12/e91bcc9a-d471-47a8-b8b4-5a51bddba04d/1_org_zoom.jpg",
            "https://cdn.dsmcdn.com/mnresize/620/920/ty1659/product/media/images/prod/PIM/20250409/12/f0cf1872-39f1-4a1c-8056-f4983e89b124/1_org_zoom.jpg",
            "https://cdn.dsmcdn.com/mnresize/620/920/ty1659/product/media/images/prod/PIM/20250408/14/db45823b-ee0e-4a5d-9d9f-4a1b1446ebc2/1_org_zoom.jpg",
            "https://cdn.dsmcdn.com/mnresize/620/920/ty1659/product/media/images/prod/PIM/20250408/14/e55689c4-b966-4690-bfba-0c68696873ce/1_org_zoom.jpg",
            "https://cdn.dsmcdn.com/mnresize/620/920/ty1658/product/media/images/prod/PIM/20250402/12/b6cfe441-d687-476c-b275-6e2911357822/1_org_zoom.jpg",
            "https://cdn.dsmcdn.com/mnresize/620/920/ty1659/product/media/images/prod/PIM/20250408/14/d0bc158e-22fc-4b5c-9834-c5c93d7077b4/1_org_zoom.jpg",
            "https://cdn.dsmcdn.com/mnresize/620/920/ty1657/product/media/images/prod/PIM/20250402/12/3ab96a39-e8af-41d2-bed5-d7632f1f9a0b/1_org_zoom.jpg",
            "https://cdn.dsmcdn.com/mnresize/620/920/ty1657/product/media/images/prod/PIM/20250402/12/1f23b8d2-03b3-4bf2-a936-a775cee1b387/1_org_zoom.jpg",
            "https://cdn.dsmcdn.com/mnresize/620/920/ty1660/product/media/images/prod/PIM/20250408/14/faac73d4-51c0-4559-9c56-4a9e99cbb49b/1_org_zoom.jpg",
            "https://cdn.dsmcdn.com/mnresize/620/920/ty1661/product/media/images/prod/PIM/20250408/14/f71f103f-8371-4c04-8ed2-f9fc6910b611/1_org_zoom.jpg",
            "https://cdn.dsmcdn.com/mnresize/-/49/ty925/product/inventory/vas/seller-logo-463180-trendyol-sigorta-1002.jpg",
            "https://cdn.dsmcdn.com/mnresize/-/49/ty924/product/inventory/vas/seller-logo-463180-trendyol-sigorta-1001.jpg",
            "https://cdn.dsmcdn.com/mnresize/-/49/ty925/product/inventory/vas/seller-logo-463180-trendyol-sigorta-1008.jpg",
            "https://cdn.dsmcdn.com/web/prod/fp/ai1_1744811068004.svg"
        ],
        "product_url": "https://www.trendyol.com/samsung/galaxy-tab-s10-fe-128-gb-10-9-mavi-tablet-p-924102587?boutiqueId=689770&merchantId=968",
        "description": "Bu ürün \nTrendyol\n tarafından gönderilecektir.\nKampanya fiyatından satılmak üzere 100 adetten fazla stok sunulmuştur.\nİncelemiş olduğunuz ürünün satış fiyatını satıcı belirlemektedir.\nÜrüne ait garanti belgesi ile tanıtma ve kullanım kılavuzları; kağıt ortamında paylaşılabileceği gibi elektronik ortamda erişim sağlayabileceğiniz, link ve karekod biçiminde de sunulabilecektir. Ürün teslimi sonrası ambalajın, paketin, kutunun dikkatle açılması tavsiye edilir.\n\nÜrün Özellikleri:\n- Kapasite: 128 GB\n- Kamera Çözünürlüğü: 5 - 10 MP\n- Bluetooth: Var\n- Garanti Tipi: Samsung TR Garantili\n- İşletim Sistemi: Android\n- Bellek Kapasitesi: 4 - 16 GB\n- Renk: Mavi\n- Sim Kart Uyumu: Yok\n- Çözünürlük: 2304 x 1440\n- İşlemci Çekirdek Sayısı: 8\n- İşlemci Tipi: Samsung\n- Ekran Boyutu: 10.9 inç\n- Ram (Sistem Belleği): 8 GB\n- Garanti Süresi: 2 Yıl\n- HDMI: Var\n- Hızlı Şarj: Var\n- Tamir Edilebilirlik: Yetkili Servis ile Tamiri Gerekir.",
        "rating": 4.682926829268292,
        "reviews_count": 451,
        "stock": 10,
        "brand": "Samsung Galaxy Tab S10 FE 128 GB 10.9\" Mavi Tablet",
        "category": "Trendyol",
        "subcategory": "Samsung > Elektronik > Bilgisayar&Tablet > Tablet Grubu > Tablet > Samsung Tablet > Elektronik > Bilgisayar&Tablet > Tablet Grubu > Tablet > Samsung Tablet > Samsung Galaxy Tab S10 FE 128 GB 10.9\" Mavi Tablet",
        "attributes": {
            "Kapasite": "128 GB",
            "Kamera Çözünürlüğü": "5 - 10 MP",
            "Bluetooth": "Var",
            "Garanti Tipi": "Samsung TR Garantili",
            "İşletim Sistemi": "Android",
            "Bellek Kapasitesi": "4 - 16 GB",
            "Renk": "Mavi",
            "Sim Kart Uyumu": "Yok",
            "Çözünürlük": "2304 x 1440",
            "İşlemci Çekirdek Sayısı": "8",
            "İşlemci Tipi": "Samsung",
            "Ekran Boyutu": "10.9 inç",
            "Ram (Sistem Belleği)": "8 GB",
            "Garanti Süresi": "2 Yıl",
            "HDMI": "Var",
            "Hızlı Şarj": "Var",
            "Tamir Edilebilirlik": "Yetkili Servis ile Tamiri Gerekir."
        },
        "additional_info": null
    }
]