{"nodes": [{"id": "users_macbook_desktop_bazarx_bazarx_mobile_app_wallet_topup_tsx", "label": "topup.tsx", "file_type": "code", "source_file": "/Users/macbook/Desktop/bazarx/bazarx-mobile/app/wallet/topup.tsx", "source_location": "L1"}, {"id": "wallet_topup_topupscreen", "label": "TopUpScreen()", "file_type": "code", "source_file": "/Users/macbook/Desktop/bazarx/bazarx-mobile/app/wallet/topup.tsx", "source_location": "L9"}], "edges": [{"source": "users_macbook_desktop_bazarx_bazarx_mobile_app_wallet_topup_tsx", "target": "react", "relation": "imports_from", "context": "import", "confidence": "EXTRACTED", "source_file": "/Users/macbook/Desktop/bazarx/bazarx-mobile/app/wallet/topup.tsx", "source_location": "L1", "weight": 1.0}, {"source": "users_macbook_desktop_bazarx_bazarx_mobile_app_wallet_topup_tsx", "target": "react_native", "relation": "imports_from", "context": "import", "confidence": "EXTRACTED", "source_file": "/Users/macbook/Desktop/bazarx/bazarx-mobile/app/wallet/topup.tsx", "source_location": "L2", "weight": 1.0}, {"source": "users_macbook_desktop_bazarx_bazarx_mobile_app_wallet_topup_tsx", "target": "react_native_safe_area_context", "relation": "imports_from", "context": "import", "confidence": "EXTRACTED", "source_file": "/Users/macbook/Desktop/bazarx/bazarx-mobile/app/wallet/topup.tsx", "source_location": "L3", "weight": 1.0}, {"source": "users_macbook_desktop_bazarx_bazarx_mobile_app_wallet_topup_tsx", "target": "vector_icons", "relation": "imports_from", "context": "import", "confidence": "EXTRACTED", "source_file": "/Users/macbook/Desktop/bazarx/bazarx-mobile/app/wallet/topup.tsx", "source_location": "L4", "weight": 1.0}, {"source": "users_macbook_desktop_bazarx_bazarx_mobile_app_wallet_topup_tsx", "target": "expo_router", "relation": "imports_from", "context": "import", "confidence": "EXTRACTED", "source_file": "/Users/macbook/Desktop/bazarx/bazarx-mobile/app/wallet/topup.tsx", "source_location": "L5", "weight": 1.0}, {"source": "users_macbook_desktop_bazarx_bazarx_mobile_app_wallet_topup_tsx", "target": "react_query", "relation": "imports_from", "context": "import", "confidence": "EXTRACTED", "source_file": "/Users/macbook/Desktop/bazarx/bazarx-mobile/app/wallet/topup.tsx", "source_location": "L6", "weight": 1.0}, {"source": "users_macbook_desktop_bazarx_bazarx_mobile_app_wallet_topup_tsx", "target": "users_macbook_desktop_bazarx_bazarx_mobile_lib_api", "relation": "imports_from", "context": "import", "confidence": "EXTRACTED", "source_file": "/Users/macbook/Desktop/bazarx/bazarx-mobile/app/wallet/topup.tsx", "source_location": "L7", "weight": 1.0}, {"source": "users_macbook_desktop_bazarx_bazarx_mobile_app_wallet_topup_tsx", "target": "lib_api_api", "relation": "imports", "context": "import", "confidence": "EXTRACTED", "source_file": "/Users/macbook/Desktop/bazarx/bazarx-mobile/app/wallet/topup.tsx", "source_location": "L7", "weight": 1.0}, {"source": "users_macbook_desktop_bazarx_bazarx_mobile_app_wallet_topup_tsx", "target": "wallet_topup_topupscreen", "relation": "contains", "confidence": "EXTRACTED", "source_file": "/Users/macbook/Desktop/bazarx/bazarx-mobile/app/wallet/topup.tsx", "source_location": "L9", "weight": 1.0}], "raw_calls": [{"caller_nid": "wallet_topup_topupscreen", "callee": "useRouter", "is_member_call": false, "source_file": "/Users/macbook/Desktop/bazarx/bazarx-mobile/app/wallet/topup.tsx", "source_location": "L10"}, {"caller_nid": "wallet_topup_topupscreen", "callee": "useQueryClient", "is_member_call": false, "source_file": "/Users/macbook/Desktop/bazarx/bazarx-mobile/app/wallet/topup.tsx", "source_location": "L11"}, {"caller_nid": "wallet_topup_topupscreen", "callee": "useState", "is_member_call": false, "source_file": "/Users/macbook/Desktop/bazarx/bazarx-mobile/app/wallet/topup.tsx", "source_location": "L12"}, {"caller_nid": "wallet_topup_topupscreen", "callee": "useState", "is_member_call": false, "source_file": "/Users/macbook/Desktop/bazarx/bazarx-mobile/app/wallet/topup.tsx", "source_location": "L13"}, {"caller_nid": "wallet_topup_topupscreen", "callee": "useMutation", "is_member_call": false, "source_file": "/Users/macbook/Desktop/bazarx/bazarx-mobile/app/wallet/topup.tsx", "source_location": "L15"}, {"caller_nid": "wallet_topup_topupscreen", "callee": "(\n    <SafeAreaView className=\"flex-1 bg-dark\">\n      <View className=\"px-6 mt-6 mb-8 flex-row items-center\">\n        <TouchableOpacity \n          className=\"w-10 h-10 bg-white/5 rounded-full items-center justify-center mr-4\"\n          onPress={() => router.back()}\n        >\n          <Text className=\"text-white\">\u2190</Text>\n        </TouchableOpacity>\n        <Text className=\"text-2xl font-black text-white\">Para Y\u00fckle</Text>\n      </View>\n\n      <ScrollView className=\"flex-1 px-6\">\n        <View className=\"bg-surface p-6 rounded-3xl border border-white/5 mb-8\">\n          <Text className=\"text-[10px] font-black text-slate-400 uppercase tracking-widest mb-4\">Y\u00fcklemek \u0130stedi\u011finiz Tutar</Text>\n          <View className=\"flex-row items-center border-b border-white/10 pb-2\">\n            <Text className=\"text-3xl font-black text-white mr-2\">\u20ba</Text>\n            <TextInput\n              className=\"flex-1 text-4xl font-black text-white\"\n              placeholder=\"0.00\"\n              placeholderTextColor=\"#1e293b\"\n              keyboardType=\"decimal-pad\"\n              value={amount}\n              onChangeText={setAmount}\n              autoFocus\n            />\n          </View>\n        </View>\n\n        <Text className=\"text-lg font-black text-white mb-4\">\u00d6deme Y\u00f6ntemi</Text>\n        <TouchableOpacity \n          onPress={()", "is_member_call": false, "source_file": "/Users/macbook/Desktop/bazarx/bazarx-mobile/app/wallet/topup.tsx", "source_location": "L41"}]}